hello_world/__init__.py
hello_world/main.py
hello_world_crock_dev-1.2.0.dist-info/LICENSE.md
hello_world_crock_dev-1.2.0.dist-info/METADATA
hello_world_crock_dev-1.2.0.dist-info/WHEEL
hello_world_crock_dev-1.2.0.dist-info/top_level.txt
hello_world_crock_dev-1.2.0.dist-info/RECORD
