Metadata-Version: 2.1
Name: hello-world-crock-dev
Version: 1.2.0
Summary: A Hello World package
Home-page: https://github.com/LeikoDmitry/hello-world
Author: Crock-dev
Author-email: leiko.dima2013@yandex.by
License: UNKNOWN
Platform: UNKNOWN
Classifier: Programming Language :: Python :: 3.8
Classifier: License :: OSI Approved :: MIT License
Classifier: Operating System :: OS Independent
Requires-Python: >=3.6
Requires-Dist: requests (<=2.24.0)
